{
"meta":{"test_sets":[],"test_metrics":[],"learn_metrics":[{"best_value":"Min","name":"RMSE"}],"launch_mode":"Train","parameters":"","iteration_count":500,"learn_sets":["learn"],"name":"experiment"},
"iterations":[
{"learn":[1.200101368],"iteration":0,"passed_time":0.001064113725,"remaining_time":0.5309927489},
{"learn":[1.050463915],"iteration":1,"passed_time":0.002211139835,"remaining_time":0.550573819},
{"learn":[0.9217037517],"iteration":2,"passed_time":0.003171208883,"remaining_time":0.5253636049},
{"learn":[0.8332778037],"iteration":3,"passed_time":0.004037716138,"remaining_time":0.5006768012},
{"learn":[0.7562267973],"iteration":4,"passed_time":0.004986786323,"remaining_time":0.4936918459},
{"learn":[0.678746241],"iteration":5,"passed_time":0.00593643413,"remaining_time":0.4887664101},
{"learn":[0.6142641528],"iteration":6,"passed_time":0.006842748569,"remaining_time":0.4819250064},
{"learn":[0.5582853074],"iteration":7,"passed_time":0.007845042573,"remaining_time":0.4824701183},
{"learn":[0.5133697305],"iteration":8,"passed_time":0.008853018743,"remaining_time":0.4829813559},
{"learn":[0.4795851075],"iteration":9,"passed_time":0.009946142135,"remaining_time":0.4873609646},
{"learn":[0.4507855205],"iteration":10,"passed_time":0.01145372858,"remaining_time":0.5091702978},
{"learn":[0.423448364],"iteration":11,"passed_time":0.01257291308,"remaining_time":0.5112984652},
{"learn":[0.4036557],"iteration":12,"passed_time":0.01376583324,"remaining_time":0.5156892912},
{"learn":[0.3900564587],"iteration":13,"passed_time":0.01549353345,"remaining_time":0.5378469469},
{"learn":[0.3755259607],"iteration":14,"passed_time":0.01706694775,"remaining_time":0.5518313107},
{"learn":[0.3618884835],"iteration":15,"passed_time":0.01845723901,"remaining_time":0.55833148},
{"learn":[0.3572804667],"iteration":16,"passed_time":0.0198631285,"remaining_time":0.5643465332},
{"learn":[0.3455325789],"iteration":17,"passed_time":0.0211400018,"remaining_time":0.5660822704},
{"learn":[0.3298098266],"iteration":18,"passed_time":0.02241866882,"remaining_time":0.5675463001},
{"learn":[0.3235798427],"iteration":19,"passed_time":0.02359571133,"remaining_time":0.566297072},
{"learn":[0.312617021],"iteration":20,"passed_time":0.02469265833,"remaining_time":0.5632277781},
{"learn":[0.3065742295],"iteration":21,"passed_time":0.02583930096,"remaining_time":0.561417539},
{"learn":[0.3005426728],"iteration":22,"passed_time":0.02687420207,"remaining_time":0.557347582},
{"learn":[0.293407748],"iteration":23,"passed_time":0.02793299309,"remaining_time":0.554004363},
{"learn":[0.2856780013],"iteration":24,"passed_time":0.0289474268,"remaining_time":0.5500011091},
{"learn":[0.2834454131],"iteration":25,"passed_time":0.03007105575,"remaining_time":0.5482184779},
{"learn":[0.2768236123],"iteration":26,"passed_time":0.03117457397,"remaining_time":0.5461323513},
{"learn":[0.2721650662],"iteration":27,"passed_time":0.03238168012,"remaining_time":0.5458626078},
{"learn":[0.2646947335],"iteration":28,"passed_time":0.03366770093,"remaining_time":0.5468099013},
{"learn":[0.2594578741],"iteration":29,"passed_time":0.03497131264,"remaining_time":0.547883898},
{"learn":[0.2550143231],"iteration":30,"passed_time":0.03666302167,"remaining_time":0.5546760375},
{"learn":[0.2519405977],"iteration":31,"passed_time":0.03785180359,"remaining_time":0.5535826275},
{"learn":[0.2469257849],"iteration":32,"passed_time":0.0390413865,"remaining_time":0.5524947726},
{"learn":[0.2394346272],"iteration":33,"passed_time":0.04075765153,"remaining_time":0.5586195769},
{"learn":[0.228404247],"iteration":34,"passed_time":0.04246994085,"remaining_time":0.5642434998},
{"learn":[0.2237416166],"iteration":35,"passed_time":0.04367106342,"remaining_time":0.562871484},
{"learn":[0.2194613523],"iteration":36,"passed_time":0.04519679116,"remaining_time":0.565570657},
{"learn":[0.217122973],"iteration":37,"passed_time":0.04634610975,"remaining_time":0.5634711238},
{"learn":[0.2159014554],"iteration":38,"passed_time":0.04764992321,"remaining_time":0.5632465282},
{"learn":[0.2133123969],"iteration":39,"passed_time":0.0487624112,"remaining_time":0.5607677288},
{"learn":[0.206498006],"iteration":40,"passed_time":0.04987808432,"remaining_time":0.5583912367},
{"learn":[0.2018796201],"iteration":41,"passed_time":0.05116580958,"remaining_time":0.5579509711},
{"learn":[0.199098738],"iteration":42,"passed_time":0.05237269117,"remaining_time":0.5566120899},
{"learn":[0.1953191458],"iteration":43,"passed_time":0.05362990406,"remaining_time":0.5558008239},
{"learn":[0.1913690193],"iteration":44,"passed_time":0.05481970473,"remaining_time":0.5542881256},
{"learn":[0.1884501576],"iteration":45,"passed_time":0.05599144416,"remaining_time":0.5526112097},
{"learn":[0.1866650466],"iteration":46,"passed_time":0.05710989292,"remaining_time":0.5504421594},
{"learn":[0.1856499667],"iteration":47,"passed_time":0.05825937123,"remaining_time":0.548609079},
{"learn":[0.1821214905],"iteration":48,"passed_time":0.05938219079,"remaining_time":0.5465585316},
{"learn":[0.1780784756],"iteration":49,"passed_time":0.06045727496,"remaining_time":0.5441154746},
{"learn":[0.175029992],"iteration":50,"passed_time":0.06149082628,"remaining_time":0.5413604117},
{"learn":[0.1725001738],"iteration":51,"passed_time":0.06263423774,"remaining_time":0.5396180482},
{"learn":[0.1716847604],"iteration":52,"passed_time":0.06388133721,"remaining_time":0.5387727874},
{"learn":[0.1706145124],"iteration":53,"passed_time":0.0652426208,"remaining_time":0.5388557199},
{"learn":[0.1683750325],"iteration":54,"passed_time":0.06662558988,"remaining_time":0.5390615909},
{"learn":[0.1677467863],"iteration":55,"passed_time":0.06788655753,"remaining_time":0.5382434204},
{"learn":[0.1649085801],"iteration":56,"passed_time":0.06918433055,"remaining_time":0.537695762},
{"learn":[0.1644437794],"iteration":57,"passed_time":0.07032829682,"remaining_time":0.535950124},
{"learn":[0.1636256942],"iteration":58,"passed_time":0.07158646521,"remaining_time":0.5350784942},
{"learn":[0.1632412918],"iteration":59,"passed_time":0.07260629487,"remaining_time":0.5324461624},
{"learn":[0.1614555466],"iteration":60,"passed_time":0.07379750177,"remaining_time":0.5311000537},
{"learn":[0.1596876746],"iteration":61,"passed_time":0.0748837233,"remaining_time":0.5290172711},
{"learn":[0.1592698421],"iteration":62,"passed_time":0.07590700029,"remaining_time":0.52652951},
{"learn":[0.1579106636],"iteration":63,"passed_time":0.07692026354,"remaining_time":0.5240192953},
{"learn":[0.1530005151],"iteration":64,"passed_time":0.07835589443,"remaining_time":0.524381755},
{"learn":[0.1507828295],"iteration":65,"passed_time":0.07965785252,"remaining_time":0.5238107272},
{"learn":[0.1494541432],"iteration":66,"passed_time":0.08088632634,"remaining_time":0.5227429747},
{"learn":[0.1484845099],"iteration":67,"passed_time":0.08204755327,"remaining_time":0.5212432796},
{"learn":[0.144933794],"iteration":68,"passed_time":0.08342648739,"remaining_time":0.5211132763},
{"learn":[0.1433298625],"iteration":69,"passed_time":0.08475910917,"remaining_time":0.5206630992},
{"learn":[0.1414095403],"iteration":70,"passed_time":0.08596084899,"remaining_time":0.5193972425},
{"learn":[0.1395372954],"iteration":71,"passed_time":0.08721681216,"remaining_time":0.5184554945},
{"learn":[0.1388228494],"iteration":72,"passed_time":0.08859437609,"remaining_time":0.518216419},
{"learn":[0.1374807201],"iteration":73,"passed_time":0.08971552763,"remaining_time":0.5164704698},
{"learn":[0.1371489792],"iteration":74,"passed_time":0.0907776635,"remaining_time":0.5144067598},
{"learn":[0.1343150694],"iteration":75,"passed_time":0.09183337186,"remaining_time":0.5123335483},
{"learn":[0.1325610766],"iteration":76,"passed_time":0.09340340529,"remaining_time":0.5131122135},
{"learn":[0.1307245425],"iteration":77,"passed_time":0.09462604043,"remaining_time":0.5119511418},
{"learn":[0.129282607],"iteration":78,"passed_time":0.09574582697,"remaining_time":0.5102404197},
{"learn":[0.1269430615],"iteration":79,"passed_time":0.09693465893,"remaining_time":0.5089069594},
{"learn":[0.125055962],"iteration":80,"passed_time":0.09802683243,"remaining_time":0.5070770714},
{"learn":[0.1237617876],"iteration":81,"passed_time":0.09908763292,"remaining_time":0.5051052508},
{"learn":[0.1232823278],"iteration":82,"passed_time":0.1002053968,"remaining_time":0.5034415718},
{"learn":[0.122157903],"iteration":83,"passed_time":0.1012398876,"remaining_time":0.5013784909},
{"learn":[0.1201600514],"iteration":84,"passed_time":0.1022250999,"remaining_time":0.499099017},
{"learn":[0.118480306],"iteration":85,"passed_time":0.1036524323,"remaining_time":0.4989779879},
{"learn":[0.1165477423],"iteration":86,"passed_time":0.1047395933,"remaining_time":0.4972120923},
{"learn":[0.1152974926],"iteration":87,"passed_time":0.105819019,"remaining_time":0.4954254074},
{"learn":[0.1132297339],"iteration":88,"passed_time":0.1072068685,"remaining_time":0.4950789096},
{"learn":[0.1117983678],"iteration":89,"passed_time":0.1085328062,"remaining_time":0.4944272282},
{"learn":[0.1108769006],"iteration":90,"passed_time":0.1099366125,"remaining_time":0.4941107091},
{"learn":[0.1105379628],"iteration":91,"passed_time":0.1112509513,"remaining_time":0.4933737841},
{"learn":[0.1092271516],"iteration":92,"passed_time":0.112481461,"remaining_time":0.4922575768},
{"learn":[0.1081617327],"iteration":93,"passed_time":0.1136465416,"remaining_time":0.4908563392},
{"learn":[0.1070854412],"iteration":94,"passed_time":0.1148166186,"remaining_time":0.489481374},
{"learn":[0.1050565046],"iteration":95,"passed_time":0.1159404493,"remaining_time":0.4879160574},
{"learn":[0.1041175198],"iteration":96,"passed_time":0.1171216709,"remaining_time":0.4865982821},
{"learn":[0.1033685738],"iteration":97,"passed_time":0.1183015543,"remaining_time":0.4852778043},
{"learn":[0.1030892255],"iteration":98,"passed_time":0.1194062277,"remaining_time":0.4836555285},
{"learn":[0.101489073],"iteration":99,"passed_time":0.1205569081,"remaining_time":0.4822276325},
{"learn":[0.1012499145],"iteration":100,"passed_time":0.1216937159,"remaining_time":0.4807504224},
{"learn":[0.0998521402],"iteration":101,"passed_time":0.1227357227,"remaining_time":0.4789099766},
{"learn":[0.09860975765],"iteration":102,"passed_time":0.1240144389,"remaining_time":0.4779974005},
{"learn":[0.09751377148],"iteration":103,"passed_time":0.1252659336,"remaining_time":0.4769741318},
{"learn":[0.09643538919],"iteration":104,"passed_time":0.1265503424,"remaining_time":0.4760703358},
{"learn":[0.09559215531],"iteration":105,"passed_time":0.1276503673,"remaining_time":0.4744740067},
{"learn":[0.09435678826],"iteration":106,"passed_time":0.1288966942,"remaining_time":0.4734243067},
{"learn":[0.09398442315],"iteration":107,"passed_time":0.1300413678,"remaining_time":0.4720020016},
{"learn":[0.09302911256],"iteration":108,"passed_time":0.1311390429,"remaining_time":0.4704161998},
{"learn":[0.09243744],"iteration":109,"passed_time":0.1323122698,"remaining_time":0.4691071385},
{"learn":[0.09229697919],"iteration":110,"passed_time":0.1334849756,"remaining_time":0.4677986982},
{"learn":[0.09217320877],"iteration":111,"passed_time":0.1346481759,"remaining_time":0.4664597524},
{"learn":[0.09123688649],"iteration":112,"passed_time":0.1357688856,"remaining_time":0.4649783957},
{"learn":[0.09052159738],"iteration":113,"passed_time":0.1368473882,"remaining_time":0.4633604549},
{"learn":[0.09019292681],"iteration":114,"passed_time":0.1378579275,"remaining_time":0.4615243659},
{"learn":[0.09009299862],"iteration":115,"passed_time":0.1388961774,"remaining_time":0.4597942426},
{"learn":[0.09000295215],"iteration":116,"passed_time":0.1403186043,"remaining_time":0.4593335507},
{"learn":[0.0888396143],"iteration":117,"passed_time":0.1415027952,"remaining_time":0.4580853201},
{"learn":[0.0873623378],"iteration":118,"passed_time":0.1427807177,"remaining_time":0.4571382642},
{"learn":[0.08665025166],"iteration":119,"passed_time":0.1441259467,"remaining_time":0.4563988312},
{"learn":[0.08655319445],"iteration":120,"passed_time":0.1458086271,"remaining_time":0.4567063609},
{"learn":[0.08612208186],"iteration":121,"passed_time":0.1471474242,"remaining_time":0.4559157898},
{"learn":[0.08560652688],"iteration":122,"passed_time":0.1482828098,"remaining_time":0.4544928398},
{"learn":[0.08471445413],"iteration":123,"passed_time":0.1494194775,"remaining_time":0.4530784157},
{"learn":[0.08429373182],"iteration":124,"passed_time":0.1505303863,"remaining_time":0.451591159},
{"learn":[0.08334548448],"iteration":125,"passed_time":0.1515290024,"remaining_time":0.4497765628},
{"learn":[0.0822395146],"iteration":126,"passed_time":0.15255198,"remaining_time":0.4480463665},
{"learn":[0.08144746561],"iteration":127,"passed_time":0.1536264761,"remaining_time":0.4464769463},
{"learn":[0.08090576959],"iteration":128,"passed_time":0.1549657084,"remaining_time":0.4456765721},
{"learn":[0.07959034068],"iteration":129,"passed_time":0.1565743517,"remaining_time":0.4456346933},
{"learn":[0.07891876397],"iteration":130,"passed_time":0.1577386849,"remaining_time":0.4443173643},
{"learn":[0.07826947741],"iteration":131,"passed_time":0.1589332679,"remaining_time":0.4430866862},
{"learn":[0.0775182816],"iteration":132,"passed_time":0.1601683549,"remaining_time":0.4419683178},
{"learn":[0.07727561901],"iteration":133,"passed_time":0.1612709945,"remaining_time":0.4404864477},
{"learn":[0.07661613852],"iteration":134,"passed_time":0.1623805019,"remaining_time":0.4390287644},
{"learn":[0.07589213116],"iteration":135,"passed_time":0.1636023893,"remaining_time":0.4378769832},
{"learn":[0.07529481864],"iteration":136,"passed_time":0.1650055824,"remaining_time":0.4372045724},
{"learn":[0.07490519074],"iteration":137,"passed_time":0.1659688566,"remaining_time":0.4353675804},
{"learn":[0.07416089447],"iteration":138,"passed_time":0.1670528489,"remaining_time":0.4338566796},
{"learn":[0.07358988134],"iteration":139,"passed_time":0.1681116287,"remaining_time":0.4322870453},
{"learn":[0.0732572556],"iteration":140,"passed_time":0.1691183164,"remaining_time":0.4305920253},
{"learn":[0.07268653795],"iteration":141,"passed_time":0.1705085796,"remaining_time":0.4298737429},
{"learn":[0.07259675217],"iteration":142,"passed_time":0.1717261582,"remaining_time":0.4287149544},
{"learn":[0.07225093844],"iteration":143,"passed_time":0.1729414904,"remaining_time":0.4275497957},
{"learn":[0.0717730178],"iteration":144,"passed_time":0.1744581539,"remaining_time":0.4271216872},
{"learn":[0.0708802692],"iteration":145,"passed_time":0.1756383027,"remaining_time":0.4258627339},
{"learn":[0.07024816104],"iteration":146,"passed_time":0.1767947821,"remaining_time":0.4245480143},
{"learn":[0.07013102085],"iteration":147,"passed_time":0.1778870421,"remaining_time":0.4230826947},
{"learn":[0.06956039],"iteration":148,"passed_time":0.1789747431,"remaining_time":0.4216116432},
{"learn":[0.06924779273],"iteration":149,"passed_time":0.1800363482,"remaining_time":0.4200848125},
{"learn":[0.06905560726],"iteration":150,"passed_time":0.1810027723,"remaining_time":0.4183441559},
{"learn":[0.06849469638],"iteration":151,"passed_time":0.1819264187,"remaining_time":0.416515748},
{"learn":[0.06779864966],"iteration":152,"passed_time":0.1829052114,"remaining_time":0.4148242377},
{"learn":[0.0674947739],"iteration":153,"passed_time":0.1839921103,"remaining_time":0.4133848711},
{"learn":[0.06674388327],"iteration":154,"passed_time":0.1856549625,"remaining_time":0.4132320134},
{"learn":[0.06640631888],"iteration":155,"passed_time":0.1869191197,"remaining_time":0.412180623},
{"learn":[0.06601896612],"iteration":156,"passed_time":0.1879735916,"remaining_time":0.4106684198},
{"learn":[0.06547071775],"iteration":157,"passed_time":0.1890603839,"remaining_time":0.4092319703},
{"learn":[0.06504695923],"iteration":158,"passed_time":0.1900702002,"remaining_time":0.407634832},
{"learn":[0.06466740967],"iteration":159,"passed_time":0.1910755061,"remaining_time":0.4060354504},
{"learn":[0.06411377192],"iteration":160,"passed_time":0.1922049645,"remaining_time":0.4047048631},
{"learn":[0.06404481848],"iteration":161,"passed_time":0.193392371,"remaining_time":0.4034976629},
{"learn":[0.06339113102],"iteration":162,"passed_time":0.1944237343,"remaining_time":0.4019680887},
{"learn":[0.06333212137],"iteration":163,"passed_time":0.1953305179,"remaining_time":0.4001893537},
{"learn":[0.06274970169],"iteration":164,"passed_time":0.1963891144,"remaining_time":0.398729414},
{"learn":[0.06269221127],"iteration":165,"passed_time":0.197351004,"remaining_time":0.3970797309},
{"learn":[0.06225573222],"iteration":166,"passed_time":0.1983196833,"remaining_time":0.3954518236},
{"learn":[0.06146343382],"iteration":167,"passed_time":0.1993876679,"remaining_time":0.3940280103},
{"learn":[0.06110303381],"iteration":168,"passed_time":0.2005127871,"remaining_time":0.3927203109},
{"learn":[0.06103266203],"iteration":169,"passed_time":0.2017282262,"remaining_time":0.3915900861},
{"learn":[0.0609604715],"iteration":170,"passed_time":0.202988344,"remaining_time":0.3905448256},
{"learn":[0.06049704719],"iteration":171,"passed_time":0.2041584174,"remaining_time":0.3893253542},
{"learn":[0.06031901411],"iteration":172,"passed_time":0.2053116833,"remaining_time":0.3880746846},
{"learn":[0.05991649743],"iteration":173,"passed_time":0.2065206616,"remaining_time":0.3869295155},
{"learn":[0.05935380104],"iteration":174,"passed_time":0.2076663916,"remaining_time":0.3856661558},
{"learn":[0.05910517961],"iteration":175,"passed_time":0.2089683065,"remaining_time":0.3846916551},
{"learn":[0.05904658644],"iteration":176,"passed_time":0.2099679889,"remaining_time":0.3831619233},
{"learn":[0.05851565826],"iteration":177,"passed_time":0.2111083942,"remaining_time":0.3818927131},
{"learn":[0.05804142828],"iteration":178,"passed_time":0.2121816747,"remaining_time":0.3805045674},
{"learn":[0.05798128661],"iteration":179,"passed_time":0.2131230864,"remaining_time":0.378885487},
{"learn":[0.05765259672],"iteration":180,"passed_time":0.2140844352,"remaining_time":0.3773090322},
{"learn":[0.05713736088],"iteration":181,"passed_time":0.2151594405,"remaining_time":0.3759379235},
{"learn":[0.05708974891],"iteration":182,"passed_time":0.2163632547,"remaining_time":0.3747931788},
{"learn":[0.05693510133],"iteration":183,"passed_time":0.2174952762,"remaining_time":0.373524496},
{"learn":[0.05651131318],"iteration":184,"passed_time":0.2185960548,"remaining_time":0.3722040933},
{"learn":[0.05611426711],"iteration":185,"passed_time":0.2198196758,"remaining_time":0.3710934313},
{"learn":[0.05587903388],"iteration":186,"passed_time":0.220994805,"remaining_time":0.3699003955},
{"learn":[0.05539168982],"iteration":187,"passed_time":0.2222519546,"remaining_time":0.3688436693},
{"learn":[0.0548966755],"iteration":188,"passed_time":0.2238398487,"remaining_time":0.3683290632},
{"learn":[0.05475029532],"iteration":189,"passed_time":0.2249499998,"remaining_time":0.3670236839},
{"learn":[0.05448850231],"iteration":190,"passed_time":0.2260798617,"remaining_time":0.365752237},
{"learn":[0.05409560872],"iteration":191,"passed_time":0.2271060861,"remaining_time":0.3643160131},
{"learn":[0.05385997162],"iteration":192,"passed_time":0.2281961876,"remaining_time":0.3629856456},
{"learn":[0.05345273057],"iteration":193,"passed_time":0.2292763467,"remaining_time":0.3616420727},
{"learn":[0.05306819915],"iteration":194,"passed_time":0.2303641871,"remaining_time":0.3603132156},
{"learn":[0.05300908886],"iteration":195,"passed_time":0.2319729653,"remaining_time":0.3597948033},
{"learn":[0.05261528868],"iteration":196,"passed_time":0.2331954159,"remaining_time":0.3586711219},
{"learn":[0.05222098659],"iteration":197,"passed_time":0.2344384824,"remaining_time":0.3575778873},
{"learn":[0.051934402],"iteration":198,"passed_time":0.2355834422,"remaining_time":0.3563347543},
{"learn":[0.05155027217],"iteration":199,"passed_time":0.2367347154,"remaining_time":0.3551020731},
{"learn":[0.05130907003],"iteration":200,"passed_time":0.2385225205,"remaining_time":0.3548170827},
{"learn":[0.05118214387],"iteration":201,"passed_time":0.2396890133,"remaining_time":0.3536006236},
{"learn":[0.05102714018],"iteration":202,"passed_time":0.2408468213,"remaining_time":0.3523719504},
{"learn":[0.05068397917],"iteration":203,"passed_time":0.2418493363,"remaining_time":0.3509186448},
{"learn":[0.05041206847],"iteration":204,"passed_time":0.242794805,"remaining_time":0.3493876462},
{"learn":[0.05015555248],"iteration":205,"passed_time":0.2438152815,"remaining_time":0.3479693824},
{"learn":[0.04975569963],"iteration":206,"passed_time":0.2447913535,"remaining_time":0.3464921091},
{"learn":[0.04935241818],"iteration":207,"passed_time":0.2458806697,"remaining_time":0.3451786325},
{"learn":[0.04916881129],"iteration":208,"passed_time":0.2471501464,"remaining_time":0.3441181464},
{"learn":[0.04904618432],"iteration":209,"passed_time":0.2483994423,"remaining_time":0.3430278013},
{"learn":[0.04896398922],"iteration":210,"passed_time":0.2496164973,"remaining_time":0.3418917902},
{"learn":[0.04864385698],"iteration":211,"passed_time":0.2508160095,"remaining_time":0.3407311828},
{"learn":[0.04813356759],"iteration":212,"passed_time":0.2518406003,"remaining_time":0.3393345178},
{"learn":[0.0478121272],"iteration":213,"passed_time":0.2528815322,"remaining_time":0.3379631692},
{"learn":[0.0476292236],"iteration":214,"passed_time":0.2539703577,"remaining_time":0.3366583811},
{"learn":[0.04755344697],"iteration":215,"passed_time":0.2550582956,"remaining_time":0.3353544258},
{"learn":[0.0475319241],"iteration":216,"passed_time":0.256073104,"remaining_time":0.3339570896},
{"learn":[0.0471527381],"iteration":217,"passed_time":0.2572973924,"remaining_time":0.3328342415},
{"learn":[0.04681012253],"iteration":218,"passed_time":0.2583997645,"remaining_time":0.3315540358},
{"learn":[0.04642405671],"iteration":219,"passed_time":0.2595186572,"remaining_time":0.3302964728},
{"learn":[0.0461862293],"iteration":220,"passed_time":0.2607553066,"remaining_time":0.329188826},
{"learn":[0.04615564627],"iteration":221,"passed_time":0.2621902735,"remaining_time":0.3283283605},
{"learn":[0.0459991999],"iteration":222,"passed_time":0.2635285526,"remaining_time":0.3273426415},
{"learn":[0.04573182449],"iteration":223,"passed_time":0.2646848379,"remaining_time":0.3261295324},
{"learn":[0.04540594178],"iteration":224,"passed_time":0.2659094052,"remaining_time":0.3250003842},
{"learn":[0.04510166839],"iteration":225,"passed_time":0.2670468159,"remaining_time":0.3237647237},
{"learn":[0.04501210293],"iteration":226,"passed_time":0.2680999892,"remaining_time":0.3224286214},
{"learn":[0.04457897613],"iteration":227,"passed_time":0.2692970028,"remaining_time":0.3212665998},
{"learn":[0.04427726231],"iteration":228,"passed_time":0.2703639734,"remaining_time":0.319950379},
{"learn":[0.04406096692],"iteration":229,"passed_time":0.2713954548,"remaining_time":0.3185946643},
{"learn":[0.04377578493],"iteration":230,"passed_time":0.2724352375,"remaining_time":0.3172514237},
{"learn":[0.0435865362],"iteration":231,"passed_time":0.2734993632,"remaining_time":0.3159389196},
{"learn":[0.04335847813],"iteration":232,"passed_time":0.2744569648,"remaining_time":0.314506479},
{"learn":[0.04315232543],"iteration":233,"passed_time":0.2753710149,"remaining_time":0.3130285896},
{"learn":[0.04298032541],"iteration":234,"passed_time":0.2762825868,"remaining_time":0.3115527043},
{"learn":[0.04260156654],"iteration":235,"passed_time":0.2773673769,"remaining_time":0.3102753708},
{"learn":[0.04225986718],"iteration":236,"passed_time":0.2784746171,"remaining_time":0.3090245751},
{"learn":[0.04221666924],"iteration":237,"passed_time":0.2796031368,"remaining_time":0.3077984111},
{"learn":[0.04192732379],"iteration":238,"passed_time":0.2805471749,"remaining_time":0.306371601},
{"learn":[0.0417793212],"iteration":239,"passed_time":0.2814867309,"remaining_time":0.3049439585},
{"learn":[0.04146258525],"iteration":240,"passed_time":0.2834256664,"remaining_time":0.3045943884},
{"learn":[0.04123192583],"iteration":241,"passed_time":0.2843648313,"remaining_time":0.3031658119},
{"learn":[0.04095581939],"iteration":242,"passed_time":0.2852473651,"remaining_time":0.3016813697},
{"learn":[0.04071980109],"iteration":243,"passed_time":0.2860707892,"remaining_time":0.3001398444},
{"learn":[0.04050848552],"iteration":244,"passed_time":0.2869634672,"remaining_time":0.2986762618},
{"learn":[0.04046825871],"iteration":245,"passed_time":0.2877858305,"remaining_time":0.2971447193},
{"learn":[0.04033950489],"iteration":246,"passed_time":0.2886397674,"remaining_time":0.2956512597},
{"learn":[0.04027275038],"iteration":247,"passed_time":0.2894899899,"remaining_time":0.2941591833},
{"learn":[0.04024712188],"iteration":248,"passed_time":0.2903255629,"remaining_time":0.2926574951},
{"learn":[0.03995825825],"iteration":249,"passed_time":0.2912089793,"remaining_time":0.2912089793},
{"learn":[0.0397296454],"iteration":250,"passed_time":0.2920384626,"remaining_time":0.2897114629},
{"learn":[0.03942380527],"iteration":251,"passed_time":0.2931798714,"remaining_time":0.2885262227},
{"learn":[0.03913790947],"iteration":252,"passed_time":0.2943372143,"remaining_time":0.2873568851},
{"learn":[0.03889519716],"iteration":253,"passed_time":0.2956908983,"remaining_time":0.2863777991},
{"learn":[0.03861668675],"iteration":254,"passed_time":0.2967701964,"remaining_time":0.2851321494},
{"learn":[0.03837467123],"iteration":255,"passed_time":0.2977609515,"remaining_time":0.2838034069},
{"learn":[0.03820738531],"iteration":256,"passed_time":0.299486629,"remaining_time":0.2831721823},
{"learn":[0.03813989775],"iteration":257,"passed_time":0.3004884007,"remaining_time":0.2818534611},
{"learn":[0.03785702683],"iteration":258,"passed_time":0.3014651523,"remaining_time":0.2805139062},
{"learn":[0.03771179233],"iteration":259,"passed_time":0.3024433659,"remaining_time":0.2791784916},
{"learn":[0.03748214644],"iteration":260,"passed_time":0.3033854465,"remaining_time":0.2778127269},
{"learn":[0.03727572676],"iteration":261,"passed_time":0.3043256038,"remaining_time":0.2764484492},
{"learn":[0.03711103856],"iteration":262,"passed_time":0.3052597963,"remaining_time":0.2750820217},
{"learn":[0.0370015865],"iteration":263,"passed_time":0.3061660359,"remaining_time":0.2736938805},
{"learn":[0.03678937235],"iteration":264,"passed_time":0.3069950356,"remaining_time":0.2722408806},
{"learn":[0.03671182624],"iteration":265,"passed_time":0.3080550828,"remaining_time":0.2709958247},
{"learn":[0.03657883848],"iteration":266,"passed_time":0.309014613,"remaining_time":0.2696644376},
{"learn":[0.03635833417],"iteration":267,"passed_time":0.3100227021,"remaining_time":0.2683778615},
{"learn":[0.03608835495],"iteration":268,"passed_time":0.311372705,"remaining_time":0.2673869697},
{"learn":[0.03587225983],"iteration":269,"passed_time":0.3126002609,"remaining_time":0.2662891112},
{"learn":[0.03570074007],"iteration":270,"passed_time":0.3136092851,"remaining_time":0.265005632},
{"learn":[0.0356105084],"iteration":271,"passed_time":0.314620432,"remaining_time":0.2637259503},
{"learn":[0.03546993141],"iteration":272,"passed_time":0.3156005277,"remaining_time":0.2624224168},
{"learn":[0.03540014839],"iteration":273,"passed_time":0.3165952117,"remaining_time":0.2611332768},
{"learn":[0.03524779276],"iteration":274,"passed_time":0.3180355801,"remaining_time":0.2602109292},
{"learn":[0.03500342298],"iteration":275,"passed_time":0.3190491379,"remaining_time":0.2589384308},
{"learn":[0.0348662342],"iteration":276,"passed_time":0.319920036,"remaining_time":0.2575529532},
{"learn":[0.03474017226],"iteration":277,"passed_time":0.3207929067,"remaining_time":0.2561727529},
{"learn":[0.03447941337],"iteration":278,"passed_time":0.3216506868,"remaining_time":0.2547842358},
{"learn":[0.03426696226],"iteration":279,"passed_time":0.3225048614,"remaining_time":0.2533966768},
{"learn":[0.03410460405],"iteration":280,"passed_time":0.3236763667,"remaining_time":0.2522602288},
{"learn":[0.03389771831],"iteration":281,"passed_time":0.3252998545,"remaining_time":0.2514729371},
{"learn":[0.03370872173],"iteration":282,"passed_time":0.3265001873,"remaining_time":0.2503552673},
{"learn":[0.03350814092],"iteration":283,"passed_time":0.3276013934,"remaining_time":0.2491616231},
{"learn":[0.03331598944],"iteration":284,"passed_time":0.3287189995,"remaining_time":0.2479809996},
{"learn":[0.03299239986],"iteration":285,"passed_time":0.3297101414,"remaining_time":0.2467061897},
{"learn":[0.03287242825],"iteration":286,"passed_time":0.3309833752,"remaining_time":0.245642714},
{"learn":[0.03272585423],"iteration":287,"passed_time":0.3320114177,"remaining_time":0.2443972936},
{"learn":[0.03261972109],"iteration":288,"passed_time":0.3330307302,"remaining_time":0.2431470037},
{"learn":[0.03254645975],"iteration":289,"passed_time":0.3340131536,"remaining_time":0.241871594},
{"learn":[0.03240908346],"iteration":290,"passed_time":0.334940993,"remaining_time":0.240558995},
{"learn":[0.03226853696],"iteration":291,"passed_time":0.3360358857,"remaining_time":0.2393680282},
{"learn":[0.03223726335],"iteration":292,"passed_time":0.337575709,"remaining_time":0.2384920538},
{"learn":[0.03220977767],"iteration":293,"passed_time":0.338680302,"remaining_time":0.2373066061},
{"learn":[0.03209935802],"iteration":294,"passed_time":0.3397829003,"remaining_time":0.2361203206},
{"learn":[0.03189930884],"iteration":295,"passed_time":0.3407876081,"remaining_time":0.2348671353},
{"learn":[0.03170176262],"iteration":296,"passed_time":0.3417267014,"remaining_time":0.2335707757},
{"learn":[0.03162612395],"iteration":297,"passed_time":0.342830563,"remaining_time":0.2323885025},
{"learn":[0.03148059326],"iteration":298,"passed_time":0.3443753443,"remaining_time":0.2315031579},
{"learn":[0.03134657439],"iteration":299,"passed_time":0.3454637927,"remaining_time":0.2303091951},
{"learn":[0.03132486723],"iteration":300,"passed_time":0.3463749915,"remaining_time":0.2289987485},
{"learn":[0.0311304875],"iteration":301,"passed_time":0.347364517,"remaining_time":0.2277422992},
{"learn":[0.03098706694],"iteration":302,"passed_time":0.3482993999,"remaining_time":0.2264520851},
{"learn":[0.03083365221],"iteration":303,"passed_time":0.349273699,"remaining_time":0.2251896217},
{"learn":[0.0307874535],"iteration":304,"passed_time":0.350509756,"remaining_time":0.2240964014},
{"learn":[0.03066784899],"iteration":305,"passed_time":0.3514369297,"remaining_time":0.2228064195},
{"learn":[0.03064775458],"iteration":306,"passed_time":0.3523165582,"remaining_time":0.2214889112},
{"learn":[0.03061181079],"iteration":307,"passed_time":0.3531729937,"remaining_time":0.2201597883},
{"learn":[0.0304222182],"iteration":308,"passed_time":0.3540923285,"remaining_time":0.2188726043},
{"learn":[0.03035016358],"iteration":309,"passed_time":0.3552094086,"remaining_time":0.2177089924},
{"learn":[0.03019111175],"iteration":310,"passed_time":0.356221766,"remaining_time":0.2164820379},
{"learn":[0.02999971625],"iteration":311,"passed_time":0.3579623309,"remaining_time":0.2156952506},
{"learn":[0.02990118915],"iteration":312,"passed_time":0.3589681671,"remaining_time":0.2144634097},
{"learn":[0.02981162955],"iteration":313,"passed_time":0.3599252607,"remaining_time":0.2132041353},
{"learn":[0.02967145335],"iteration":314,"passed_time":0.3610796346,"remaining_time":0.2120626426},
{"learn":[0.02943215657],"iteration":315,"passed_time":0.3619510783,"remaining_time":0.2107563241},
{"learn":[0.02939716063],"iteration":316,"passed_time":0.3633807468,"remaining_time":0.2097750053},
{"learn":[0.02922728286],"iteration":317,"passed_time":0.364462363,"remaining_time":0.2085916669},
{"learn":[0.02898691866],"iteration":318,"passed_time":0.3653374978,"remaining_time":0.2072918091},
{"learn":[0.02884689379],"iteration":319,"passed_time":0.3661300472,"remaining_time":0.2059481515},
{"learn":[0.02880013874],"iteration":320,"passed_time":0.3669623658,"remaining_time":0.2046301043},
{"learn":[0.02871947173],"iteration":321,"passed_time":0.3677713088,"remaining_time":0.2033021521},
{"learn":[0.02865669538],"iteration":322,"passed_time":0.3685612039,"remaining_time":0.2019669755},
{"learn":[0.02847931702],"iteration":323,"passed_time":0.3695000498,"remaining_time":0.2007160764},
{"learn":[0.0283283285],"iteration":324,"passed_time":0.370508588,"remaining_time":0.1995046243},
{"learn":[0.02820669299],"iteration":325,"passed_time":0.3714671247,"remaining_time":0.1982677291},
{"learn":[0.02802574912],"iteration":326,"passed_time":0.3723349345,"remaining_time":0.1969845372},
{"learn":[0.02801153916],"iteration":327,"passed_time":0.3731679789,"remaining_time":0.1956856474},
{"learn":[0.02787902167],"iteration":328,"passed_time":0.3740726377,"remaining_time":0.1944268117},
{"learn":[0.02777024079],"iteration":329,"passed_time":0.3749720835,"remaining_time":0.1931674369},
{"learn":[0.02775868418],"iteration":330,"passed_time":0.3761193049,"remaining_time":0.1920367448},
{"learn":[0.02771305173],"iteration":331,"passed_time":0.3770638134,"remaining_time":0.1908033754},
{"learn":[0.02757872364],"iteration":332,"passed_time":0.3780060582,"remaining_time":0.1895706057},
{"learn":[0.02750470206],"iteration":333,"passed_time":0.3787941287,"remaining_time":0.1882629502},
{"learn":[0.02749179235],"iteration":334,"passed_time":0.3796073317,"remaining_time":0.1869707753},
{"learn":[0.0274017063],"iteration":335,"passed_time":0.3804174364,"remaining_time":0.1856799392},
{"learn":[0.02728415911],"iteration":336,"passed_time":0.3812454202,"remaining_time":0.1844006038},
{"learn":[0.02726981112],"iteration":337,"passed_time":0.382079151,"remaining_time":0.1831266937},
{"learn":[0.02715793213],"iteration":338,"passed_time":0.3836420632,"remaining_time":0.1822016878},
{"learn":[0.02702326779],"iteration":339,"passed_time":0.3844649325,"remaining_time":0.1809246741},
{"learn":[0.02686236573],"iteration":340,"passed_time":0.3854752848,"remaining_time":0.1797377428},
{"learn":[0.02670204269],"iteration":341,"passed_time":0.3866538781,"remaining_time":0.1786295694},
{"learn":[0.02667556526],"iteration":342,"passed_time":0.3878654055,"remaining_time":0.1775360602},
{"learn":[0.0265986192],"iteration":343,"passed_time":0.388715957,"remaining_time":0.1762781666},
{"learn":[0.02646561826],"iteration":344,"passed_time":0.3898392914,"remaining_time":0.1751451889},
{"learn":[0.02630353753],"iteration":345,"passed_time":0.3908131153,"remaining_time":0.1739457218},
{"learn":[0.02628180082],"iteration":346,"passed_time":0.3918070183,"remaining_time":0.1727564087},
{"learn":[0.02619680791],"iteration":347,"passed_time":0.39280779,"remaining_time":0.1715712186},
{"learn":[0.0261195813],"iteration":348,"passed_time":0.3937379167,"remaining_time":0.1703565198},
{"learn":[0.02611233738],"iteration":349,"passed_time":0.3946310399,"remaining_time":0.1691275885},
{"learn":[0.02599934608],"iteration":350,"passed_time":0.3959427495,"remaining_time":0.1680782612},
{"learn":[0.02596598681],"iteration":351,"passed_time":0.3968742524,"remaining_time":0.1668675834},
{"learn":[0.02590881109],"iteration":352,"passed_time":0.3978451474,"remaining_time":0.1656748914},
{"learn":[0.02588729075],"iteration":353,"passed_time":0.3987508198,"remaining_time":0.1644565528},
{"learn":[0.02577727891],"iteration":354,"passed_time":0.3995325541,"remaining_time":0.1631893531},
{"learn":[0.02572299093],"iteration":355,"passed_time":0.4004479388,"remaining_time":0.1619789415},
{"learn":[0.02561135186],"iteration":356,"passed_time":0.4014492321,"remaining_time":0.1608045944},
{"learn":[0.02541849187],"iteration":357,"passed_time":0.4026349645,"remaining_time":0.1597043714},
{"learn":[0.02533189522],"iteration":358,"passed_time":0.4038239354,"remaining_time":0.158604944},
{"learn":[0.02521668426],"iteration":359,"passed_time":0.4048336981,"remaining_time":0.157435327},
{"learn":[0.02512587192],"iteration":360,"passed_time":0.4058558522,"remaining_time":0.1562713669},
{"learn":[0.02498093783],"iteration":361,"passed_time":0.4070308353,"remaining_time":0.155166451},
{"learn":[0.02484991906],"iteration":362,"passed_time":0.4079597819,"remaining_time":0.1539682923},
{"learn":[0.02478538692],"iteration":363,"passed_time":0.4090485465,"remaining_time":0.1528313251},
{"learn":[0.02474258507],"iteration":364,"passed_time":0.4100735023,"remaining_time":0.1516710214},
{"learn":[0.02461244201],"iteration":365,"passed_time":0.4111022141,"remaining_time":0.1505128325},
{"learn":[0.02456580886],"iteration":366,"passed_time":0.4119985336,"remaining_time":0.1493073705},
{"learn":[0.02447867538],"iteration":367,"passed_time":0.4129354789,"remaining_time":0.1481181609},
{"learn":[0.02441563909],"iteration":368,"passed_time":0.4138216277,"remaining_time":0.1469122852},
{"learn":[0.02434597513],"iteration":369,"passed_time":0.4150249787,"remaining_time":0.1458195871},
{"learn":[0.02425493105],"iteration":370,"passed_time":0.4164565354,"remaining_time":0.1448056417},
{"learn":[0.02421312846],"iteration":371,"passed_time":0.4176750428,"remaining_time":0.1437161437},
{"learn":[0.02413871433],"iteration":372,"passed_time":0.4187321962,"remaining_time":0.1425710159},
{"learn":[0.02405059622],"iteration":373,"passed_time":0.4198067335,"remaining_time":0.141432215},
{"learn":[0.02385306075],"iteration":374,"passed_time":0.4207850836,"remaining_time":0.1402616945},
{"learn":[0.02369269698],"iteration":375,"passed_time":0.4221997415,"remaining_time":0.139236085},
{"learn":[0.02355853478],"iteration":376,"passed_time":0.4233079692,"remaining_time":0.1381084356},
{"learn":[0.02350707082],"iteration":377,"passed_time":0.4243691103,"remaining_time":0.1369656917},
{"learn":[0.02341949782],"iteration":378,"passed_time":0.4252742879,"remaining_time":0.1357735853},
{"learn":[0.02334179055],"iteration":379,"passed_time":0.4262238421,"remaining_time":0.1345970028},
{"learn":[0.0232421241],"iteration":380,"passed_time":0.427196052,"remaining_time":0.1334286882},
{"learn":[0.02322116674],"iteration":381,"passed_time":0.4283612715,"remaining_time":0.132321021},
{"learn":[0.02317737226],"iteration":382,"passed_time":0.4292714964,"remaining_time":0.1311351569},
{"learn":[0.02311490465],"iteration":383,"passed_time":0.4302770336,"remaining_time":0.1299795206},
{"learn":[0.02304951407],"iteration":384,"passed_time":0.4311341876,"remaining_time":0.1287803417},
{"learn":[0.02297256511],"iteration":385,"passed_time":0.4322368599,"remaining_time":0.1276554457},
{"learn":[0.02290036602],"iteration":386,"passed_time":0.4331713847,"remaining_time":0.1264815671},
{"learn":[0.0227296479],"iteration":387,"passed_time":0.434436535,"remaining_time":0.1254043606},
{"learn":[0.02265538297],"iteration":388,"passed_time":0.4355485782,"remaining_time":0.1242824992},
{"learn":[0.02253144093],"iteration":389,"passed_time":0.436761148,"remaining_time":0.1231890417},
{"learn":[0.02245531705],"iteration":390,"passed_time":0.4378805467,"remaining_time":0.1220690015},
{"learn":[0.02236873695],"iteration":391,"passed_time":0.4389368262,"remaining_time":0.1209315746},
{"learn":[0.02226830961],"iteration":392,"passed_time":0.4399159485,"remaining_time":0.1197735534},
{"learn":[0.02226080366],"iteration":393,"passed_time":0.4409711769,"remaining_time":0.1186369156},
{"learn":[0.02221173737],"iteration":394,"passed_time":0.4418996772,"remaining_time":0.1174670028},
{"learn":[0.02217738513],"iteration":395,"passed_time":0.4429233809,"remaining_time":0.1163233121},
{"learn":[0.02207957278],"iteration":396,"passed_time":0.4438727044,"remaining_time":0.1151609284},
{"learn":[0.02192677364],"iteration":397,"passed_time":0.4447563443,"remaining_time":0.1139827817},
{"learn":[0.02191230028],"iteration":398,"passed_time":0.4456184179,"remaining_time":0.1128006521},
{"learn":[0.02188484212],"iteration":399,"passed_time":0.4464903603,"remaining_time":0.1116225901},
{"learn":[0.02188196474],"iteration":400,"passed_time":0.4478500459,"remaining_time":0.1105664702},
{"learn":[0.02182317793],"iteration":401,"passed_time":0.4490366755,"remaining_time":0.1094666522},
{"learn":[0.02174563832],"iteration":402,"passed_time":0.4501346328,"remaining_time":0.1083450605},
{"learn":[0.02164241218],"iteration":403,"passed_time":0.4511171223,"remaining_time":0.1071961479},
{"learn":[0.02153880219],"iteration":404,"passed_time":0.4521421766,"remaining_time":0.1060580414},
{"learn":[0.02153272269],"iteration":405,"passed_time":0.4531043348,"remaining_time":0.1049059297},
{"learn":[0.02140245043],"iteration":406,"passed_time":0.4546892235,"remaining_time":0.1038970461},
{"learn":[0.02133360031],"iteration":407,"passed_time":0.4556416921,"remaining_time":0.1027427345},
{"learn":[0.0212066924],"iteration":408,"passed_time":0.4567469432,"remaining_time":0.101623403},
{"learn":[0.0210981067],"iteration":409,"passed_time":0.4577818796,"remaining_time":0.1004887053},
{"learn":[0.02103469784],"iteration":410,"passed_time":0.4589666241,"remaining_time":0.0993869332},
{"learn":[0.02094791757],"iteration":411,"passed_time":0.4600315292,"remaining_time":0.09825916158},
{"learn":[0.02088389146],"iteration":412,"passed_time":0.4614051751,"remaining_time":0.0971967318},
{"learn":[0.0207757401],"iteration":413,"passed_time":0.4626320577,"remaining_time":0.09610231151},
{"learn":[0.02071544057],"iteration":414,"passed_time":0.4638802672,"remaining_time":0.095011621},
{"learn":[0.02062531026],"iteration":415,"passed_time":0.4650355378,"remaining_time":0.09390140667},
{"learn":[0.02055228236],"iteration":416,"passed_time":0.4660105258,"remaining_time":0.09275509266},
{"learn":[0.02045626524],"iteration":417,"passed_time":0.4674608126,"remaining_time":0.09170283884},
{"learn":[0.02039689518],"iteration":418,"passed_time":0.4684098259,"remaining_time":0.09055178019},
{"learn":[0.02037197625],"iteration":419,"passed_time":0.4693673315,"remaining_time":0.08940330124},
{"learn":[0.02027297528],"iteration":420,"passed_time":0.470335426,"remaining_time":0.08825771653},
{"learn":[0.02025874421],"iteration":421,"passed_time":0.4712361928,"remaining_time":0.08710052853},
{"learn":[0.02014043955],"iteration":422,"passed_time":0.4721294305,"remaining_time":0.08594318238},
{"learn":[0.02012421088],"iteration":423,"passed_time":0.4730225456,"remaining_time":0.08478706007},
{"learn":[0.02011508847],"iteration":424,"passed_time":0.4742737677,"remaining_time":0.08369537078},
{"learn":[0.02005250916],"iteration":425,"passed_time":0.4752945713,"remaining_time":0.08256290675},
{"learn":[0.01999197831],"iteration":426,"passed_time":0.4762660471,"remaining_time":0.08142253264},
{"learn":[0.01988989799],"iteration":427,"passed_time":0.477145194,"remaining_time":0.08026741582},
{"learn":[0.01976114738],"iteration":428,"passed_time":0.4780745738,"remaining_time":0.07912189916},
{"learn":[0.01963253628],"iteration":429,"passed_time":0.4792791573,"remaining_time":0.0780221884},
{"learn":[0.01956725102],"iteration":430,"passed_time":0.4807597175,"remaining_time":0.07696617287},
{"learn":[0.01956459152],"iteration":431,"passed_time":0.4817350778,"remaining_time":0.07582866965},
{"learn":[0.0194504374],"iteration":432,"passed_time":0.4827779059,"remaining_time":0.07470235495},
{"learn":[0.01944248433],"iteration":433,"passed_time":0.48370829,"remaining_time":0.0735593252},
{"learn":[0.01939064844],"iteration":434,"passed_time":0.4846353108,"remaining_time":0.07241677058},
{"learn":[0.01931527839],"iteration":435,"passed_time":0.4856419896,"remaining_time":0.07128689756},
{"learn":[0.01930266024],"iteration":436,"passed_time":0.4866547341,"remaining_time":0.07015846281},
{"learn":[0.0191958146],"iteration":437,"passed_time":0.4879084072,"remaining_time":0.06906466038},
{"learn":[0.01909478548],"iteration":438,"passed_time":0.489205348,"remaining_time":0.06797614175},
{"learn":[0.01906591422],"iteration":439,"passed_time":0.490226768,"remaining_time":0.06684910473},
{"learn":[0.01900717045],"iteration":440,"passed_time":0.4912914117,"remaining_time":0.06572832946},
{"learn":[0.01897041701],"iteration":441,"passed_time":0.4923058867,"remaining_time":0.06460122495},
{"learn":[0.01893192627],"iteration":442,"passed_time":0.4935056534,"remaining_time":0.06349847008},
{"learn":[0.01885422312],"iteration":443,"passed_time":0.4947306135,"remaining_time":0.06239845576},
{"learn":[0.01880948379],"iteration":444,"passed_time":0.4958514008,"remaining_time":0.06128500459},
{"learn":[0.01876251675],"iteration":445,"passed_time":0.4969941321,"remaining_time":0.06017417743},
{"learn":[0.01875762909],"iteration":446,"passed_time":0.4980116965,"remaining_time":0.0590483667},
{"learn":[0.01869898149],"iteration":447,"passed_time":0.4990434417,"remaining_time":0.0579246852},
{"learn":[0.01863863105],"iteration":448,"passed_time":0.5001819956,"remaining_time":0.05681354516},
{"learn":[0.01858431518],"iteration":449,"passed_time":0.501211233,"remaining_time":0.055690137},
{"learn":[0.01857676763],"iteration":450,"passed_time":0.5021632461,"remaining_time":0.05455875623},
{"learn":[0.01851492299],"iteration":451,"passed_time":0.5030411173,"remaining_time":0.05342029564},
{"learn":[0.01848136457],"iteration":452,"passed_time":0.504001744,"remaining_time":0.05229157167},
{"learn":[0.01843471597],"iteration":453,"passed_time":0.5050360038,"remaining_time":0.05117104884},
{"learn":[0.01839945633],"iteration":454,"passed_time":0.5061667412,"remaining_time":0.05006044693},
{"learn":[0.01835040685],"iteration":455,"passed_time":0.5070845925,"remaining_time":0.04892921506},
{"learn":[0.01826675727],"iteration":456,"passed_time":0.5080147396,"remaining_time":0.04780007396},
{"learn":[0.01812704675],"iteration":457,"passed_time":0.5089613203,"remaining_time":0.04667330885},
{"learn":[0.01805271121],"iteration":458,"passed_time":0.5103790057,"remaining_time":0.04558941009},
{"learn":[0.01796176174],"iteration":459,"passed_time":0.5114197258,"remaining_time":0.04447128051},
{"learn":[0.01789937184],"iteration":460,"passed_time":0.5125494953,"remaining_time":0.04336102021},
{"learn":[0.01785940044],"iteration":461,"passed_time":0.5138348424,"remaining_time":0.04226347189},
{"learn":[0.01777025819],"iteration":462,"passed_time":0.5148998696,"remaining_time":0.04114750578},
{"learn":[0.01763994333],"iteration":463,"passed_time":0.5158717177,"remaining_time":0.04002452982},
{"learn":[0.01757084823],"iteration":464,"passed_time":0.5168786187,"remaining_time":0.03890484227},
{"learn":[0.01753793108],"iteration":465,"passed_time":0.5178160355,"remaining_time":0.03778056912},
{"learn":[0.01749865286],"iteration":466,"passed_time":0.5190653947,"remaining_time":0.03667913924},
{"learn":[0.01739278926],"iteration":467,"passed_time":0.5201366148,"remaining_time":0.03556489674},
{"learn":[0.01734537728],"iteration":468,"passed_time":0.5211717124,"remaining_time":0.03444845008},
{"learn":[0.01729370945],"iteration":469,"passed_time":0.5221967936,"remaining_time":0.03333171023},
{"learn":[0.01727872406],"iteration":470,"passed_time":0.5233984961,"remaining_time":0.03222623437},
{"learn":[0.01725777761],"iteration":471,"passed_time":0.5245076325,"remaining_time":0.03111485955},
{"learn":[0.01722795584],"iteration":472,"passed_time":0.5259067102,"remaining_time":0.03002004477},
{"learn":[0.01714558532],"iteration":473,"passed_time":0.5270024323,"remaining_time":0.02890730641},
{"learn":[0.01709064976],"iteration":474,"passed_time":0.5281295822,"remaining_time":0.0277962938},
{"learn":[0.01707356544],"iteration":475,"passed_time":0.5291528448,"remaining_time":0.02667997537},
{"learn":[0.016969565],"iteration":476,"passed_time":0.5304329969,"remaining_time":0.02557643381},
{"learn":[0.0169236007],"iteration":477,"passed_time":0.5313590446,"remaining_time":0.02445585561},
{"learn":[0.01689686338],"iteration":478,"passed_time":0.5326456699,"remaining_time":0.02335189784},
{"learn":[0.01685355853],"iteration":479,"passed_time":0.5337917413,"remaining_time":0.02224132255},
{"learn":[0.01681275687],"iteration":480,"passed_time":0.5348616997,"remaining_time":0.02112759313},
{"learn":[0.01676237699],"iteration":481,"passed_time":0.5357873391,"remaining_time":0.02000865582},
{"learn":[0.01673240042],"iteration":482,"passed_time":0.536701609,"remaining_time":0.01889011874},
{"learn":[0.01665169526],"iteration":483,"passed_time":0.5376232839,"remaining_time":0.01777267054},
{"learn":[0.01656782212],"iteration":484,"passed_time":0.5385917507,"remaining_time":0.01665747682},
{"learn":[0.01650269669],"iteration":485,"passed_time":0.5396217814,"remaining_time":0.01554466037},
{"learn":[0.01648275726],"iteration":486,"passed_time":0.5410995188,"remaining_time":0.014444135},
{"learn":[0.0164485086],"iteration":487,"passed_time":0.5422981975,"remaining_time":0.01333520158},
{"learn":[0.01641842658],"iteration":488,"passed_time":0.5437712683,"remaining_time":0.01223207352},
{"learn":[0.01633090774],"iteration":489,"passed_time":0.5448247822,"remaining_time":0.01111887311},
{"learn":[0.01626735228],"iteration":490,"passed_time":0.5457870529,"remaining_time":0.01000424333},
{"learn":[0.01625675033],"iteration":491,"passed_time":0.5467926917,"remaining_time":0.008890938077},
{"learn":[0.01620904978],"iteration":492,"passed_time":0.5478076959,"remaining_time":0.007778202578},
{"learn":[0.01614412652],"iteration":493,"passed_time":0.5488381153,"remaining_time":0.006666049983},
{"learn":[0.01611007756],"iteration":494,"passed_time":0.5501052226,"remaining_time":0.00555661841},
{"learn":[0.01604718889],"iteration":495,"passed_time":0.5512038489,"remaining_time":0.00444519233},
{"learn":[0.01600153471],"iteration":496,"passed_time":0.5522183454,"remaining_time":0.003333309932},
{"learn":[0.01594652578],"iteration":497,"passed_time":0.5532991294,"remaining_time":0.002222084857},
{"learn":[0.01587355811],"iteration":498,"passed_time":0.5543003149,"remaining_time":0.001110822274},
{"learn":[0.01583246936],"iteration":499,"passed_time":0.5551268053,"remaining_time":0}
]}